{
  "id": "mark.powell@enron.com",
  "name": "Mark Powell",
  "email": "mark.powell@enron.com",
  "community_id": 9,
  "metrics": {
    "in_degree_centrality": 0.000878348704435661,
    "out_degree_centrality": 0.0,
    "degree_centrality": 0.000878348704435661,
    "betweenness_centrality": 0.0,
    "eigenvector_centrality": 0.015081981541677197,
    "pagerank": 0.00021522288499581325
  },
  "sentiment": {
    "avg_sent": 0,
    "avg_received": 0.0845
  },
  "dead_man_switch": {
    "id": "mark.powell@enron.com",
    "name": "Mark Powell",
    "dms_score": -0.2836,
    "betweenness": 0.0,
    "eigenvector": 0.015082,
    "redundancy": 0.9954,
    "impact_pct": 0.5
  },
  "waste": {
    "id": "mark.powell@enron.com",
    "name": "Mark Powell",
    "waste_score": 0,
    "overproduction": 0,
    "broadcast_ratio": 0,
    "reply_all_ratio": 0,
    "orphan_ratio": 0
  },
  "connections": [
    {
      "id": "tana.jones@enron.com",
      "name": "Tana Jones",
      "direction": "incoming",
      "email_count": 34,
      "weight": 0.1732,
      "sentiment": 0.0717
    },
    {
      "id": "janette.elbertson@enron.com",
      "name": "Janette Elbertson",
      "direction": "incoming",
      "email_count": 6,
      "weight": 0.1463,
      "sentiment": 0.1483
    },
    {
      "id": "elizabeth.sager@enron.com",
      "name": "Elizabeth Sager",
      "direction": "incoming",
      "email_count": 4,
      "weight": 0.1446,
      "sentiment": 0.0997
    },
    {
      "id": "mark.taylor@enron.com",
      "name": "Mark Taylor",
      "direction": "incoming",
      "email_count": 5,
      "weight": 0.1308,
      "sentiment": 0.0535
    }
  ]
}