{
  "id": "robbi.rossi@enron.com",
  "name": "Robbi Rossi",
  "email": "robbi.rossi@enron.com",
  "community_id": 9,
  "metrics": {
    "in_degree_centrality": 0.0006587615283267457,
    "out_degree_centrality": 0.0,
    "degree_centrality": 0.0006587615283267457,
    "betweenness_centrality": 0.0,
    "eigenvector_centrality": 0.014365246896710256,
    "pagerank": 0.0002132102316315074
  },
  "sentiment": {
    "avg_sent": 0,
    "avg_received": -0.0166
  },
  "dead_man_switch": {
    "id": "robbi.rossi@enron.com",
    "name": "Robbi Rossi",
    "dms_score": -0.2843,
    "betweenness": 0.0,
    "eigenvector": 0.014365,
    "redundancy": 0.9954,
    "impact_pct": 0.5
  },
  "waste": {
    "id": "robbi.rossi@enron.com",
    "name": "Robbi Rossi",
    "waste_score": 0,
    "overproduction": 0,
    "broadcast_ratio": 0,
    "reply_all_ratio": 0,
    "orphan_ratio": 0
  },
  "connections": [
    {
      "id": "tana.jones@enron.com",
      "name": "Tana Jones",
      "direction": "incoming",
      "email_count": 314,
      "weight": 0.2387,
      "sentiment": -0.0343
    },
    {
      "id": "marie.heard@enron.com",
      "name": "Marie Heard",
      "direction": "incoming",
      "email_count": 53,
      "weight": 0.1855,
      "sentiment": 0.0783
    },
    {
      "id": "mark.taylor@enron.com",
      "name": "Mark Taylor",
      "direction": "incoming",
      "email_count": 3,
      "weight": 0.1468,
      "sentiment": 0.1158
    }
  ]
}